queue_service/__init__.py
queue_service/aws_queue.py
queue_service/azure_queue.py
queue_service/base.py
queue_service/example_usage.py
queue_service/exceptions.py
queue_service/factory.py
queue_service/queue_message.py
queue_service/utils.py
queue_service-0.1.8.dist-info/licenses/LICENSE
queue_service-0.1.8.dist-info/METADATA
queue_service-0.1.8.dist-info/WHEEL
queue_service-0.1.8.dist-info/top_level.txt
queue_service-0.1.8.dist-info/RECORD
