Metadata-Version: 2.4
Name: queue_service
Version: 0.1.8
Summary: A unified cloud db package for AWS, Azure, and GCP for Queue Service
Author: Aaditya Muleva, Vinay Shankar Miryala, Aakash Kag
Author-email: aaditya.muleva@trovehealth.io, vinay.miryala@trovehealth.io, aakash.kag@trovehealth.io
License: MIT
Classifier: Programming Language :: Python :: 3
Classifier: License :: OSI Approved :: MIT License
Classifier: Operating System :: OS Independent
Classifier: Development Status :: 5 - Production/Stable
Classifier: Intended Audience :: Developers
Classifier: Topic :: Software Development :: Libraries :: Python Modules
Requires-Python: >=3.6
License-File: LICENSE
Requires-Dist: azure-storage-queue
Dynamic: author
Dynamic: author-email
Dynamic: classifier
Dynamic: description
Dynamic: description-content-type
Dynamic: license
Dynamic: license-file
Dynamic: requires-dist
Dynamic: requires-python
Dynamic: summary
